[
 {
  "additional_discount_percentage": 0.0,
  "address_display": null,
  "amended_from": null,
  "apply_discount_on": "Grand Total",
  "auto_repeat": null,
  "base_discount_amount": 0.0,
  "base_grand_total": 972.0,
  "base_in_words": "INR Nine Hundred And Seventy Two only.",
  "base_net_total": 900.0,
  "base_rounded_total": 972.0,
  "base_rounding_adjustment": 0.0,
  "base_total": 900.0,
  "base_total_taxes_and_charges": 72.0,
  "billing_address_gstin": null,
  "campaign": null,
  "company": "RCM PRO (Demo)",
  "company_address": null,
  "company_address_display": null,
  "company_gstin": "",
  "competitors": [],
  "contact_display": null,
  "contact_email": null,
  "contact_mobile": null,
  "contact_person": null,
  "conversion_rate": 1.0,
  "coupon_code": null,
  "currency": "INR",
  "custom_amended": null,
  "custom_link_chnc": [],
  "custom_ref_by": null,
  "customer_address": null,
  "customer_group": "Demo Customer Group",
  "customer_name": "Grant Plastics Ltd.",
  "discount_amount": 0.0,
  "docstatus": 1,
  "doctype": "Quotation",
  "enq_det": null,
  "grand_total": 972.0,
  "group_same_items": 0,
  "gst_category": "Unregistered",
  "ignore_pricing_rule": 0,
  "in_words": "INR Nine Hundred And Seventy Two only.",
  "incoterm": null,
  "is_export_with_gst": 0,
  "is_reverse_charge": 0,
  "items": [
   {
    "actual_qty": 0.0,
    "additional_notes": null,
    "against_blanket_order": 0,
    "amount": 900.0,
    "base_amount": 900.0,
    "base_net_amount": 900.0,
    "base_net_rate": 900.0,
    "base_price_list_rate": 900.0,
    "base_rate": 900.0,
    "base_rate_with_margin": 0.0,
    "blanket_order": null,
    "blanket_order_rate": 0.0,
    "brand": null,
    "cess_amount": 0.0,
    "cess_non_advol_amount": 0.0,
    "cess_non_advol_rate": 0.0,
    "cess_rate": 0.0,
    "cgst_amount": 0.0,
    "cgst_rate": 0.0,
    "conversion_factor": 1.0,
    "customer_item_code": null,
    "description": "Camera",
    "discount_amount": 0.0,
    "discount_percentage": 0.0,
    "gross_profit": 900.0,
    "gst_hsn_code": null,
    "gst_treatment": "Taxable",
    "has_alternative_item": 0,
    "igst_amount": 0.0,
    "igst_rate": 0.0,
    "image": "https://images.pexels.com/photos/51383/photo-camera-subject-photographer-51383.jpeg",
    "is_alternative": 0,
    "is_free_item": 0,
    "item_code": "SKU010",
    "item_group": "Demo Item Group",
    "item_name": "Camera",
    "item_tax_rate": "{\"Sales - RPD\": 4.0, \"Service - RPD\": 4.0}",
    "item_tax_template": "In 8 - RPD",
    "margin_rate_or_amount": 0.0,
    "margin_type": "",
    "net_amount": 900.0,
    "net_rate": 900.0,
    "page_break": 0,
    "parent": "SAL-QTN-2024-00004",
    "parentfield": "items",
    "parenttype": "Quotation",
    "prevdoc_docname": null,
    "prevdoc_doctype": null,
    "price_list_rate": 900.0,
    "pricing_rules": "",
    "projected_qty": 0.0,
    "qty": 1.0,
    "rate": 900.0,
    "rate_with_margin": 0.0,
    "sgst_amount": 0.0,
    "sgst_rate": 0.0,
    "stock_qty": 1.0,
    "stock_uom": "Nos",
    "stock_uom_rate": 900.0,
    "taxable_value": 0.0,
    "total_weight": 0.0,
    "uom": "Nos",
    "valuation_rate": 0.0,
    "warehouse": null,
    "weight_per_unit": 0.0,
    "weight_uom": null
   }
  ],
  "language": "en",
  "letter_head": null,
  "lost_reasons": [],
  "modified": "2024-03-05 23:51:53.701558",
  "name": "SAL-QTN-2024-00004",
  "named_place": null,
  "naming_series": "SAL-QTN-.YYYY.-",
  "net_total": 900.0,
  "opportunity": null,
  "order_lost_reason": null,
  "order_type": "Sales",
  "other_charges_calculation": "<div class=\"tax-break-up\" style=\"overflow-x: auto;\">\n\t<table class=\"table table-bordered table-hover\">\n\t\t<thead>\n\t\t\t<tr>\n\t\t\t\t\n\t\t\t\t\t\n\t\t\t\t\t\t<th class=\"text-left\">HSN/SAC</th>\n\t\t\t\t\t\n\t\t\t\t\n\t\t\t\t\t\n\t\t\t\t\t\t<th class=\"text-right\">Taxable Amount</th>\n\t\t\t\t\t\n\t\t\t\t\n\t\t\t\t\t\n\t\t\t\t\t\t<th class=\"text-right\">Sales</th>\n\t\t\t\t\t\n\t\t\t\t\n\t\t\t\t\t\n\t\t\t\t\t\t<th class=\"text-right\">Service</th>\n\t\t\t\t\t\n\t\t\t\t\n\t\t\t</tr>\n\t\t</thead>\n\t\t<tbody>\n\t\t\t\n\t\t\t\t<tr>\n\t\t\t\t\t<td>None</td>\n\t\t\t\t\t<td class=\"text-right\">\n\t\t\t\t\t\t\n\t\t\t\t\t\t\t₹ 900.00\n\t\t\t\t\t\t\n\t\t\t\t\t</td>\n\t\t\t\t\t\n\t\t\t\t\t\t\n\t\t\t\t\t\t\n\t\t\t\t\t\t\t<td class=\"text-right\">\n\t\t\t\t\t\t\t\t\n\t\t\t\t\t\t\t\t\t(4.0%)\n\t\t\t\t\t\t\t\t\n\t\t\t\t\t\t\t\t\n\t\t\t\t\t\t\t\t\t₹ 36.00\n\t\t\t\t\t\t\t\t\n\t\t\t\t\t\t\t</td>\n\t\t\t\t\t\t\n\t\t\t\t\t\n\t\t\t\t\t\t\n\t\t\t\t\t\t\n\t\t\t\t\t\t\t<td class=\"text-right\">\n\t\t\t\t\t\t\t\t\n\t\t\t\t\t\t\t\t\t(4.0%)\n\t\t\t\t\t\t\t\t\n\t\t\t\t\t\t\t\t\n\t\t\t\t\t\t\t\t\t₹ 36.00\n\t\t\t\t\t\t\t\t\n\t\t\t\t\t\t\t</td>\n\t\t\t\t\t\t\n\t\t\t\t\t\n\t\t\t\t</tr>\n\t\t\t\n\t\t</tbody>\n\t</table>\n</div>",
  "packed_items": [],
  "party_name": "Grant Plastics Ltd.",
  "payment_schedule": [
   {
    "base_payment_amount": 972.0,
    "description": null,
    "discount": 0.0,
    "discount_date": null,
    "discount_type": null,
    "discounted_amount": 0.0,
    "due_date": "2024-03-05",
    "invoice_portion": 100.0,
    "mode_of_payment": null,
    "outstanding": 972.0,
    "paid_amount": 0.0,
    "parent": "SAL-QTN-2024-00004",
    "parentfield": "payment_schedule",
    "parenttype": "Quotation",
    "payment_amount": 972.0,
    "payment_term": null
   }
  ],
  "payment_terms_template": null,
  "place_of_supply": "03-Punjab",
  "plc_conversion_rate": 1.0,
  "price_list_currency": "INR",
  "pricing_rules": [],
  "quotation_to": "Customer",
  "referral_sales_partner": null,
  "rounded_total": 972.0,
  "rounding_adjustment": 0.0,
  "scan_barcode": null,
  "select_print_heading": null,
  "selling_price_list": "Standard Selling",
  "shipping_address": null,
  "shipping_address_name": null,
  "shipping_rule": null,
  "source": null,
  "status": "Open",
  "supplier_quotation": null,
  "tax_category": "In State",
  "taxes": [
   {
    "account_currency": "INR",
    "account_head": "Sales - RPD",
    "base_tax_amount": 36.0,
    "base_tax_amount_after_discount_amount": 36.0,
    "base_total": 936.0,
    "charge_type": "On Net Total",
    "cost_center": "Main - RPD",
    "description": "Sales",
    "dont_recompute_tax": 0,
    "included_in_paid_amount": 0,
    "included_in_print_rate": 0,
    "item_wise_tax_detail": "{\"SKU010\":[4.0,36.0]}",
    "parent": "SAL-QTN-2024-00004",
    "parentfield": "taxes",
    "parenttype": "Quotation",
    "rate": 0.0,
    "row_id": null,
    "tax_amount": 36.0,
    "tax_amount_after_discount_amount": 36.0,
    "total": 936.0
   },
   {
    "account_currency": "INR",
    "account_head": "Service - RPD",
    "base_tax_amount": 36.0,
    "base_tax_amount_after_discount_amount": 36.0,
    "base_total": 972.0,
    "charge_type": "On Net Total",
    "cost_center": "Main - RPD",
    "description": "Service",
    "dont_recompute_tax": 0,
    "included_in_paid_amount": 0,
    "included_in_print_rate": 0,
    "item_wise_tax_detail": "{\"SKU010\":[4.0,36.0]}",
    "parent": "SAL-QTN-2024-00004",
    "parentfield": "taxes",
    "parenttype": "Quotation",
    "rate": 0.0,
    "row_id": null,
    "tax_amount": 36.0,
    "tax_amount_after_discount_amount": 36.0,
    "total": 972.0
   }
  ],
  "taxes_and_charges": null,
  "tc_name": null,
  "terms": null,
  "territory": null,
  "title": "Grant Plastics Ltd.",
  "total": 900.0,
  "total_net_weight": 0.0,
  "total_qty": 1.0,
  "total_taxes_and_charges": 72.0,
  "transaction_date": "2024-03-05",
  "valid_till": "2024-04-05"
 }
]